lambdapdk/__init__.py
lambdapdk/asap7/__init__.py
lambdapdk/asap7/libs/asap7sc7p5t.py
lambdapdk/asap7/libs/fakeio7.py
lambdapdk/asap7/libs/fakekit7.py
lambdapdk/asap7/libs/fakeram7.py
lambdapdk/freepdk45/__init__.py
lambdapdk/freepdk45/libs/fakeram45.py
lambdapdk/freepdk45/libs/nangate45.py
lambdapdk/gf180/__init__.py
lambdapdk/gf180/libs/gf180io.py
lambdapdk/gf180/libs/gf180mcu.py
lambdapdk/gf180/libs/gf180sram.py
lambdapdk/ihp130/__init__.py
lambdapdk/ihp130/libs/sg13g2_io.py
lambdapdk/ihp130/libs/sg13g2_sram.py
lambdapdk/ihp130/libs/sg13g2_stdcell.py
lambdapdk/interposer/__init__.py
lambdapdk/interposer/_generator.py
lambdapdk/interposer/libs/bumps.py
lambdapdk/sky130/__init__.py
lambdapdk/sky130/libs/sky130io.py
lambdapdk/sky130/libs/sky130sc.py
lambdapdk/sky130/libs/sky130sram.py
lambdapdk-0.2.4.dist-info/licenses/LICENSE
lambdapdk-0.2.4.dist-info/METADATA
lambdapdk-0.2.4.dist-info/WHEEL
lambdapdk-0.2.4.dist-info/entry_points.txt
lambdapdk-0.2.4.dist-info/top_level.txt
lambdapdk-0.2.4.dist-info/RECORD
