Metadata-Version: 2.4
Name: lambdapdk
Version: 0.2.4
Summary: Library of open source Process Design Kits
Author: Zero ASIC
License:                                  Apache License
Project-URL: Homepage, https://github.com/siliconcompiler/lambdapdk
Requires-Python: >=3.8
License-File: LICENSE
Requires-Dist: siliconcompiler>=0.35.0
Requires-Dist: lambdalib>=0.5.0
Provides-Extra: test
Requires-Dist: flake8==7.3.0; extra == "test"
Requires-Dist: pytest==8.4.2; extra == "test"
Requires-Dist: pytest-timeout==2.4.0; extra == "test"
Requires-Dist: tclint==0.6.1; extra == "test"
Requires-Dist: sc-leflib==0.4.0; extra == "test"
Requires-Dist: Jinja2==3.1.6; extra == "test"
Dynamic: license-file
